CHANGES.rst
CONTRIBUTORS.rst
MANIFEST.in
README.rst
setup.cfg
setup.py
docs/LICENSE.GPL
docs/LICENSE.rst
docs/index.rst
src/jazkarta/__init__.py
src/jazkarta.tesserae.egg-info/PKG-INFO
src/jazkarta.tesserae.egg-info/SOURCES.txt
src/jazkarta.tesserae.egg-info/dependency_links.txt
src/jazkarta.tesserae.egg-info/entry_points.txt
src/jazkarta.tesserae.egg-info/namespace_packages.txt
src/jazkarta.tesserae.egg-info/not-zip-safe
src/jazkarta.tesserae.egg-info/requires.txt
src/jazkarta.tesserae.egg-info/top_level.txt
src/jazkarta/tesserae/__init__.py
src/jazkarta/tesserae/background.py
src/jazkarta/tesserae/collection.py
src/jazkarta/tesserae/config.py
src/jazkarta/tesserae/configure.zcml
src/jazkarta/tesserae/interfaces.py
src/jazkarta/tesserae/setuphandlers.py
src/jazkarta/tesserae/slider.py
src/jazkarta/tesserae/summary.py
src/jazkarta/tesserae/testing.py
src/jazkarta/tesserae/utils.py
src/jazkarta/tesserae/browser/__init__.py
src/jazkarta/tesserae/browser/configure.zcml
src/jazkarta/tesserae/browser/slider.pt
src/jazkarta/tesserae/browser/slider.py
src/jazkarta/tesserae/browser/overrides/.gitkeep
src/jazkarta/tesserae/browser/static/.gitkeep
src/jazkarta/tesserae/browser/static/animate.css
src/jazkarta/tesserae/browser/static/bs-carousel.less
src/jazkarta/tesserae/browser/static/jazkarta-tesserae-compiled.css
src/jazkarta/tesserae/browser/static/jazkarta-tesserae-compiled.css.map
src/jazkarta/tesserae/browser/static/jazkarta-tesserae-compiled.js
src/jazkarta/tesserae/browser/static/jazkarta-tesserae-compiled.js.map
src/jazkarta/tesserae/browser/static/mosaic-fixes.less
src/jazkarta/tesserae/browser/static/scripts.js
src/jazkarta/tesserae/browser/static/styles.less
src/jazkarta/tesserae/locales/jazkarta.tesserae.pot
src/jazkarta/tesserae/locales/update.sh
src/jazkarta/tesserae/profiles/common/browserlayer.xml
src/jazkarta/tesserae/profiles/common/metadata.xml
src/jazkarta/tesserae/profiles/common/registry.xml
src/jazkarta/tesserae/profiles/common/types.xml
src/jazkarta/tesserae/profiles/common/workflows.xml
src/jazkarta/tesserae/profiles/common/types/Folder.xml
src/jazkarta/tesserae/profiles/common/types/sliderimage.xml
src/jazkarta/tesserae/profiles/plone-4.3/cssregistry.xml
src/jazkarta/tesserae/profiles/plone-4.3/jsregistry.xml
src/jazkarta/tesserae/profiles/plone-4.3/metadata.xml
