Metadata-Version: 2.1
Name: jazkarta.tesserae
Version: 1.1.0
Summary: A collection of tiles and styles for Plone and Mosaic.
Home-page: https://pypi.python.org/pypi/jazkarta.tesserae
Author: Jazkarta
Author-email: info@jazkarta.com
License: GPL version 2
Keywords: Python Plone
Platform: UNKNOWN
Classifier: Environment :: Web Environment
Classifier: Framework :: Plone
Classifier: Framework :: Plone :: 4.3
Classifier: Framework :: Plone :: 5.0
Classifier: Framework :: Plone :: 5.2
Classifier: Programming Language :: Python
Classifier: Programming Language :: Python :: 2.7
Classifier: Programming Language :: Python :: 3.6
Classifier: Programming Language :: Python :: 3.7
Classifier: Operating System :: OS Independent
Classifier: License :: OSI Approved :: GNU General Public License v2 (GPLv2)
Provides-Extra: test
